azureml/__init__.py
azureml/contrib/__init__.py
azureml/contrib/brainwave/__init__.py
azureml/contrib/brainwave/brainwave_image.py
azureml/contrib/brainwave/brainwave_webservice.py
azureml/contrib/brainwave/client.py
azureml/contrib/brainwave/_cli/__init__.py
azureml/contrib/brainwave/_cli/cmd_brainwave_image.py
azureml/contrib/brainwave/_cli/cmd_brainwave_webservice.py
azureml/contrib/brainwave/data/brainwave_image_payload_template.json
azureml/contrib/brainwave/data/brainwave_service_payload_template.json
azureml/contrib/brainwave/external/__init__.py
azureml/contrib/brainwave/external/tensorflow/__init__.py
azureml/contrib/brainwave/external/tensorflow/graph_util_impl.py
azureml/contrib/brainwave/external/tensorflow_serving/__init__.py
azureml/contrib/brainwave/external/tensorflow_serving/apis/__init__.py
azureml/contrib/brainwave/external/tensorflow_serving/apis/classification_pb2.py
azureml/contrib/brainwave/external/tensorflow_serving/apis/get_model_metadata_pb2.py
azureml/contrib/brainwave/external/tensorflow_serving/apis/inference_pb2.py
azureml/contrib/brainwave/external/tensorflow_serving/apis/input_pb2.py
azureml/contrib/brainwave/external/tensorflow_serving/apis/model_pb2.py
azureml/contrib/brainwave/external/tensorflow_serving/apis/predict_pb2.py
azureml/contrib/brainwave/external/tensorflow_serving/apis/prediction_service_pb2.py
azureml/contrib/brainwave/external/tensorflow_serving/apis/prediction_service_pb2_grpc.py
azureml/contrib/brainwave/external/tensorflow_serving/apis/regression_pb2.py
azureml/contrib/brainwave/models/__init__.py
azureml/contrib/brainwave/models/brainwave_model.py
azureml/contrib/brainwave/models/densenet121.py
azureml/contrib/brainwave/models/resnet152.py
azureml/contrib/brainwave/models/resnet50.py
azureml/contrib/brainwave/models/utils.py
azureml/contrib/brainwave/models/vgg16.py
azureml/contrib/brainwave/pipeline/__init__.py
azureml/contrib/brainwave/pipeline/abstract_stage.py
azureml_contrib_brainwave-1.0.33.dist-info/DESCRIPTION.rst
azureml_contrib_brainwave-1.0.33.dist-info/LICENSE.txt
azureml_contrib_brainwave-1.0.33.dist-info/METADATA
azureml_contrib_brainwave-1.0.33.dist-info/RECORD
azureml_contrib_brainwave-1.0.33.dist-info/WHEEL
azureml_contrib_brainwave-1.0.33.dist-info/metadata.json
azureml_contrib_brainwave-1.0.33.dist-info/top_level.txt
